process_data_5/__init__.py
process_data_5/setup.py
process_data_5-0.2.dist-info/METADATA
process_data_5-0.2.dist-info/WHEEL
process_data_5-0.2.dist-info/top_level.txt
process_data_5-0.2.dist-info/RECORD
