Metadata-Version: 2.1
Name: process-data-5
Version: 0.2
Summary: Data processing for the SEAT mobility advisor project
Home-page: UNKNOWN
Author: PSantaView
Author-email: UNKNOWN
License: MIT
Platform: UNKNOWN
